contactcenter_broadcaster/__init__.py
contactcenter_broadcaster/__main__.py
contactcenter_broadcaster/asterisk.py
contactcenter_broadcaster/configuration.py
contactcenter_broadcaster/controller.py
contactcenter_broadcaster/database.py
contactcenter_broadcaster/exception.py
contactcenter_broadcaster/logger.py
contactcenter_broadcaster/service.py
contactcenter_broadcaster/tool.py
contactcenter_broadcaster/websocket.py
contactcenter_broadcaster/worker.py
contactcenter_broadcaster/resources/config.yaml
contactcenter_broadcaster-0.0.1.dist-info/DESCRIPTION.rst
contactcenter_broadcaster-0.0.1.dist-info/METADATA
contactcenter_broadcaster-0.0.1.dist-info/RECORD
contactcenter_broadcaster-0.0.1.dist-info/WHEEL
contactcenter_broadcaster-0.0.1.dist-info/metadata.json
contactcenter_broadcaster-0.0.1.dist-info/top_level.txt
