Metadata-Version: 2.0
Name: contactcenter-broadcaster
Version: 0.0.1
Summary: UNKNOWN
Home-page: UNKNOWN
Author: UNKNOWN
Author-email: UNKNOWN
License: UNKNOWN
Platform: UNKNOWN
Requires-Dist: aiohttp (>=2.0.0)
Requires-Dist: aiohttp-debugger
Requires-Dist: aiomysql (>=0.0.9)
Requires-Dist: motor (>=1.1)
Requires-Dist: openpyxl (>=2.4.1)
Requires-Dist: panoramisk (>=1.1)
Requires-Dist: pymysql (>=0.7.9)
Requires-Dist: ruamel.yaml (>=0.13.11)
Requires-Dist: uvloop (>=0.7.2)
Requires-Dist: voluptuous (>=0.9.3)
